Dock2.py
Dock2-0.1.0.dist-info/LICENSE.txt
Dock2-0.1.0.dist-info/METADATA
Dock2-0.1.0.dist-info/WHEEL
Dock2-0.1.0.dist-info/top_level.txt
Dock2-0.1.0.dist-info/RECORD
