Metadata-Version: 2.1
Name: Dock2
Version: 0.1.0
Summary: Simple wrapper for interacting with h2cs drivers (HTTP2 ClearText)
Home-page: https://github.com/Mwimwii/Dock2
Author: goooby
Author-email: qdyd65@gmail.com
License: UNKNOWN
Platform: UNKNOWN
Classifier: Programming Language :: Python :: 3
Classifier: Programming Language :: Python :: 3.6
Classifier: Programming Language :: Python :: 3.7
Classifier: Programming Language :: Python :: 3.8
Classifier: Development Status :: 2 - Pre-Alpha
Classifier: License :: OSI Approved :: MIT License
Classifier: Topic :: Internet :: WWW/HTTP
Classifier: Topic :: Internet :: Proxy Servers
Classifier: Topic :: Security
Classifier: Operating System :: OS Independent
Requires-Dist: h2
Provides-Extra: dev
Requires-Dist: pytest (>=3.7) ; extra == 'dev'
